{"_id":{"$oid":"5cd982c509393a3617354d7e"},"concernedDepartment":["SI"],"name":"Linköping university","country":"Suède","url_to_website":"https://liu.se/en","courses":[{"date_added":{"$date":"2019-05-13T14:28:20.479Z"},"_id":{"$oid":"5cd9802a09393a3617354d56"},"name":"Concurrent Programming and Operating Systems","semester":7,"link_to_courses":"https://liu.se/studieinfo/en/kurs/tddb68/vt-2019","ECTS_count":6,"major":"SI","description":"Threads..."},{"date_added":{"$date":"2019-05-13T14:28:20.479Z"},"_id":{"$oid":"5cd9804409393a3617354d57"},"name":"Information Security, Second Course","semester":7,"link_to_courses":"https://liu.se/studieinfo/en/kurs/tddd17/vt-2019","ECTS_count":6,"major":"SI","description":"Security"},{"date_added":{"$date":"2019-05-13T14:28:20.479Z"},"_id":{"$oid":"5cd9806109393a3617354d58"},"name":"Distributed Systems","semester":7,"link_to_courses":"https://liu.se/studieinfo/en/kurs/tddd25/vt-2019","ECTS_count":6,"major":"SI","description":"Distributed Systems"},{"date_added":{"$date":"2019-05-13T14:28:20.479Z"},"_id":{"$oid":"5cd9809009393a3617354d59"},"name":"Advanced Programming in C++","semester":7,"link_to_courses":"https://liu.se/studieinfo/en/kurs/tddd38/vt-2019","ECTS_count":6,"major":"SI","description":"Programmation orienté objet"},{"date_added":{"$date":"2019-05-13T14:28:20.479Z"},"_id":{"$oid":"5cd980d109393a3617354d5a"},"name":"Algorithmic Problem Solving","semester":7,"link_to_courses":"https://liu.se/studieinfo/en/kurs/tddd95/vt-2019","ECTS_count":6,"major":"SI","description":"Alogrithmes et structure de données"},{"date_added":{"$date":"2019-05-13T14:28:20.479Z"},"_id":{"$oid":"5cd9811709393a3617354d5b"},"name":"Web Programming","semester":7,"link_to_courses":"https://liu.se/studieinfo/en/kurs/tddd97/vt-2019","ECTS_count":6,"major":"SI","description":"Programmation Web Angular"},{"date_added":{"$date":"2019-05-13T14:28:20.479Z"},"_id":{"$oid":"5cd9813c09393a3617354d5c"},"name":"Natural Language Processing","semester":7,"link_to_courses":"https://liu.se/studieinfo/en/kurs/tdde09/vt-2019","ECTS_count":6,"major":"SI","description":"Traitement du langage"}],"rankings":[],"__v":0}
{"_id":{"$oid":"5cd9830f09393a3617354d86"},"concernedDepartment":["MAM","SI"],"name":"Trinity College","country":"Irelande","url_to_website":"https://www.tcd.ie/","courses":[{"date_added":{"$date":"2019-05-13T14:28:20.479Z"},"_id":{"$oid":"5cd9847209393a3617354d90"},"name":"Réalité virtuelle / Réalité augmentée","semester":7,"link_to_courses":"https://www.tcd.ie/","ECTS_count":6,"major":"SI","description":"Ce cours de réalité augmentée propose de nombreuses options : machine learning, mathématiques appliquées à la lumière et au son, ..."},{"date_added":{"$date":"2019-05-13T14:28:20.479Z"},"_id":{"$oid":"5cd9856409393a3617354d91"},"name":"Data Science","semester":7,"link_to_courses":"https://www.tcd.ie/courses/postgraduate/az/course.php?id=DPTCS-DASC-1F09","ECTS_count":6,"major":"SI","description":"Ce cours traite d'applications concrètes de Data Science dans le domaine de la santé, des finances, du transport..."},{"date_added":{"$date":"2019-05-13T14:28:20.479Z"},"_id":{"$oid":"5cd9866409393a3617354d92"},"name":"Systèmes intelligents","semester":7,"link_to_courses":"https://www.tcd.ie/courses/postgraduate/az/course.php?id=DPTCS-MINS-1F09","ECTS_count":6,"major":"SI","description":"Ce cours se focalise principalemnt sur des applications web, et nécéssite d'avoir des connaissances en web design, en intelligence artificielle et en bases de données."},{"date_added":{"$date":"2019-05-13T14:28:20.479Z"},"_id":{"$oid":"5cd9891109393a3617354d93"},"name":"Sécurité et vie privée","semester":7,"link_to_courses":"https://scss.tcd.ie/modules/?m=CS7NS5","ECTS_count":5,"major":"SI","description":"L'objectif de ce cours est de développer des compétences en analyse des risques, en cryptographie, ..."},{"date_added":{"$date":"2019-05-13T14:28:20.479Z"},"_id":{"$oid":"5cd98a5509393a3617354d94"},"name":"Innovation","semester":7,"link_to_courses":"https://scss.tcd.ie/modules/?m=CS7CS2","ECTS_count":5,"major":"SI","description":"Ce cours traite d'analyses de marché, de création d'entreprise, ..."},{"date_added":{"$date":"2019-05-13T14:28:20.479Z"},"_id":{"$oid":"5cd98b0a09393a3617354d95"},"name":"Management des systèmes d'information","semester":7,"link_to_courses":"https://www.tcd.ie/courses/postgraduate/az/course.php?id=DPTCS-MISY-1P09","ECTS_count":6,"major":"SI","description":"Ce cours se présente sous forme de projet, et aborde des notions particulièrement variées, comme par exemple l'impact social des systèmes d'informations, ..."},{"date_added":{"$date":"2019-05-13T14:28:20.479Z"},"_id":{"$oid":"5cd98b7109393a3617354d96"},"name":"Statistics","semester":7,"link_to_courses":"https://www.tcd.ie/courses/postgraduate/az/course.php?id=DPCCS-STAT-1P09","ECTS_count":6,"major":"SI","description":"Ce cours est une brève introduction aux statistiques et aux mathématiques appliquées aux données."}],"rankings":[],"__v":7}
